portable_app_framework/README.md
portable_app_framework/__init__.py
portable_app_framework/app_template/README.md
portable_app_framework/app_template/__init__.py
portable_app_framework/app_template/analyze.py
portable_app_framework/app_template/config.yaml
portable_app_framework/app_template/manifest.ttl
portable_app_framework/app_template/preprocess.py
portable_app_framework/app_template/query.rq
portable_app_framework/libraries/Brick-nightly.ttl
portable_app_framework/libraries/Brick-subset.ttl
portable_app_framework/libraries/Brick.ttl
portable_app_framework/libraries/constraints.ttl
portable_app_framework/utils/__init__.py
portable_app_framework/utils/logger.py
portable_app_framework/utils/util.py
portable_app_framework/utils/util_brick.py
portable_app_framework/utils/util_qualify.py
pfb_toolkit-0.1.11.dist-info/LICENSE.md
pfb_toolkit-0.1.11.dist-info/METADATA
pfb_toolkit-0.1.11.dist-info/WHEEL
pfb_toolkit-0.1.11.dist-info/entry_points.txt
pfb_toolkit-0.1.11.dist-info/RECORD
