Metadata-Version: 2.1
Name: pfb-toolkit
Version: 0.1.11
Summary: Portable Framework for Building Applications - PFB-Toolkit
Home-page: https://github.com/baeda-polito/portable-app-framework
License: MIT
Keywords: energy,data,analysis,pandas
Author: RobertoChiosa
Author-email: roberto.chiosa@polito.it
Maintainer: RobertoChiosa
Maintainer-email: roberto.chiosa@polito.it
Requires-Python: >=3.11,<4.0
Classifier: Development Status :: 3 - Alpha
Classifier: Intended Audience :: Developers
Classifier: License :: OSI Approved :: MIT License
Classifier: Operating System :: OS Independent
Classifier: Programming Language :: Python :: 3
Classifier: Programming Language :: Python :: 3.11
Classifier: Programming Language :: Python :: 3.12
Classifier: Programming Language :: Python :: 3 :: Only
Classifier: Topic :: Software Development
Requires-Dist: buildingmotif (>=0.2.0b0,<0.3.0)
Requires-Dist: inquirer (>=3.3.0,<4.0.0)
Requires-Dist: pandas (>=2.2.2,<3.0.0)
Requires-Dist: pyshacl (==0.21)
Requires-Dist: pytest (>=8.2.2,<9.0.0)
Requires-Dist: setuptools (>=65.7.0,<66.0.0)
Project-URL: Documentation, https://github.com/baeda-polito/portable-app-framework
Project-URL: Repository, https://github.com/baeda-polito/portable-app-framework
